sstar/__init__.py
sstar/__main__.py
sstar/cal_match_rate.py
sstar/cal_s_star.py
sstar/cal_threshold.py
sstar/conftest.py
sstar/get_quantile.py
sstar/get_tract.py
sstar/utils.py
sstar-1.1.3.dist-info/LICENSE
sstar-1.1.3.dist-info/METADATA
sstar-1.1.3.dist-info/WHEEL
sstar-1.1.3.dist-info/entry_points.txt
sstar-1.1.3.dist-info/top_level.txt
sstar-1.1.3.dist-info/RECORD
