Metadata-Version: 2.1
Name: sstar
Version: 1.1.3
Summary: A Python package for detecting archaic introgression from population genetic data with S*
Home-page: https://github.com/xin-huang/sstar
Author: Xin Huang
Author-email: xinhuang.res@gmail.com
License: Apache-2.0
Classifier: License :: OSI Approved :: Apache Software License
Classifier: Programming Language :: Python
Classifier: Programming Language :: Python :: 3
License-File: LICENSE
Requires-Dist: demes
Requires-Dist: numpy
Requires-Dist: pandas
Requires-Dist: rpy2
Requires-Dist: scikit-allel
Requires-Dist: scipy
